xbcompiler/__init__.py
xbcompiler/__main__.py
xbcompiler/main.py
xbcompiler-0.0.4.dist-info/LICENSE
xbcompiler-0.0.4.dist-info/METADATA
xbcompiler-0.0.4.dist-info/WHEEL
xbcompiler-0.0.4.dist-info/top_level.txt
xbcompiler-0.0.4.dist-info/RECORD
