Metadata-Version: 2.1
Name: xbcompiler
Version: 0.0.4
Summary: Xilia Base Compiler (XLA => LUA)
Author-email: Artemii Kravchuk <artemiykra@gmail.com>
Classifier: Programming Language :: Python :: 3
Classifier: License :: OSI Approved :: GNU General Public License v3 (GPLv3)
Classifier: Operating System :: OS Independent
Requires-Python: >=3.12.4
License-File: LICENSE
Requires-Dist: loguru
